surfflow/__init__.py
surfflow/defaults.json
surfflow/firetasks/__init__.py
surfflow/firetasks/convergence.py
surfflow/firetasks/core.py
surfflow/firetasks/database.py
surfflow/firetasks/start_swfs.py
surfflow/firetasks/surfen_tools.py
surfflow/firetasks/vasp.py
surfflow/gui/__init__.py
surfflow/gui/app.py
surfflow/phys/__init__.py
surfflow/phys/surfen.py
surfflow/phys/wulff.py
surfflow/scripts/__init__.py
surfflow/scripts/colorful_test.py
surfflow/scripts/main.py
surfflow/scripts/submit.py
surfflow/tests/__init__.py
surfflow/tests/convergence_test.py
surfflow/tests/example_submit.py
surfflow/utils/__init__.py
surfflow/utils/convergence.py
surfflow/utils/db_tools.py
surfflow/utils/misc_tools.py
surfflow/utils/structure_manipulation.py
surfflow/utils/surfen_tools.py
surfflow/workflows/__init__.py
surfflow/workflows/main.py
surfflow/workflows/subworkflows.py
surfflow-1.0.5.dist-info/LICENSE
surfflow-1.0.5.dist-info/METADATA
surfflow-1.0.5.dist-info/WHEEL
surfflow-1.0.5.dist-info/entry_points.txt
surfflow-1.0.5.dist-info/top_level.txt
surfflow-1.0.5.dist-info/RECORD
