Metadata-Version: 2.1
Name: surfflow
Version: 1.0.5
Summary: Calculate surface energies of arbitrary crystals.
Author-email: Firat Yalcin <firat.yalcin@univie.ac.at>, Michael Wolloch <michael.wolloch@univie.ac.at>
License: MIT License
Keywords: tribology,surface energy,surface,wulff shape,wulff construction
Classifier: License :: OSI Approved :: MIT License
Classifier: Programming Language :: Python
Classifier: Programming Language :: Python :: 3
Requires-Python: >=3.9
License-File: LICENSE
Requires-Dist: atomate
Requires-Dist: pymatgen ==2023.12.18
Requires-Dist: custodian
Requires-Dist: fireworks
Requires-Dist: numpy ==1.26.4
Requires-Dist: ruamel.yaml ==0.17.40
Requires-Dist: streamlit
Requires-Dist: htflow-utils[workflows]
Requires-Dist: colorful
